[{"agent":"Alex Watson","userType":"Active Client","policy_mode":"12","producer":"Brandie Placencia","policy_number":"YEEX9MOIBU7X","premium_amount_written":"","premium_amount":"1180.83","policy_type":"Single","company_name":"Integon Gen Ins Corp","category_name":"Commercial Auto","policy_start_date":"02-11-2018","policy_end_date":"02-11-2019","csr":"Tami Ellison","account_name":"Lura Lucca & Owen Dodson","email":"madler@yahoo.ca","gender":"","firstname":"Lura Lucca","city":"MOCKSVILLE","account_type":"Commercial","phone":"8677356559","address":"170 MATTHIAS CT","state":"NC","zip":"27028","dob":"11-02-1960","primary":"","ApplicantID":"","agency_id":"","hasActive":"","ClientPolicy":""},{"agent":"Alex Watson","userType":"Active Client","policy_mode":"12","producer":"Sol Birney","policy_number":"7CZ3CLKWMSKH","premium_amount_written":"","premium_amount":"2105.9","policy_type":"Single","company_name":"Integon Ind Corp","category_name":"Commercial Auto","policy_start_date":"09-11-2018","policy_end_date":"09-11-2019","csr":"Molly Eaton","account_name":"Torie Buchanan & Glenda Ruiz","email":"mbalazin@mac.com","gender":"","firstname":"Torie Buchanan","city":"WINSTON SALEM","account_type":"Commercial","phone":"6094964988","address":"910 DELMONTE DR","state":"NC","zip":"27106","dob":"17-10-1946","primary":"","ApplicantID":"","agency_id":"","hasActive":"","ClientPolicy":""},{"agent":"Alex Watson","userType":"Active Client","policy_mode":"12","producer":"Yee Ribble","policy_number":"ZSB972578CRV","premium_amount_written":"","premium_amount":"2105.9","policy_type":"Single","company_name":"Integon Ind Corp","category_name":"Commercial Auto","policy_start_date":"09-11-2018","policy_end_date":"09-11-2019","csr":"Gordon Carey","account_name":"Sebastian Scarberry & Jonah Bishop","email":"maikelnai@msn.com","gender":"","firstname":"Sebastian Scarberry","city":"WINSTON SALEM","account_type":"Commercial","phone":"6888541383","address":"910 DELMONTE DR","state":"NC","zip":"27106","dob":"20-08-1958","primary":"","ApplicantID":"","agency_id":"","hasActive":"","ClientPolicy":""},{"agent":"Alex Watson","userType":"Active Client","policy_mode":"6","producer":"Carmella Landers","policy_number":"JRWJV5U5XWE4","premium_amount_written":"","premium_amount":"1323.63","policy_type":"Single","company_name":"Nationwide Prop & Cas Ins Co_Copy","category_name":"Personal Auto","policy_start_date":"31-12-2018","policy_end_date":"30-06-2019","csr":"Cliff Alvarez","account_name":"Vergie Hardesty & Wilma Wong","email":"killmenow@me.com","gender":"","firstname":"Vergie Hardesty","city":"Winston Salem","account_type":"Commercial","phone":"4183346713","address":"301 N Main St Ste 2100","state":"NC","zip":"27101-3843","dob":"20-08-1958","primary":"","ApplicantID":"","agency_id":"","hasActive":"","ClientPolicy":""},{"agent":"Alex Watson","userType":"Active Client","policy_mode":"6","producer":"Jared Roan","policy_number":"AUU730H3S5JU","premium_amount_written":"","premium_amount":"1323.63","policy_type":"Single","company_name":"Nationwide Prop & Cas Ins Co_Copy","category_name":"Personal Auto","policy_start_date":"31-12-2018","policy_end_date":"30-06-2019","csr":"Jan Hensley","account_name":"Omar Rossbach & Laurie Ortega","email":"bhtower@hotmail.com","gender":"","firstname":"Omar Rossbach","city":"Winston Salem","account_type":"Commercial","phone":"7645408831","address":"301 N Main St Ste 2100","state":"NC","zip":"27101-3843","dob":"20-11-1949","primary":"","ApplicantID":"","agency_id":"","hasActive":"","ClientPolicy":""},{"agent":"Alex Watson","userType":"Active Client","policy_mode":"6","producer":"Victorina Ebert","policy_number":"60G18LYQO157","premium_amount_written":"","premium_amount":"729.13","policy_type":"Single","company_name":"Nationwide Prop & Cas Ins Co_Copy","category_name":"Personal Auto","policy_start_date":"07-12-2018","policy_end_date":"07-06-2019","csr":"Cara Mccoy","account_name":"Lucius Galeana & Efren Pena","email":"whimsy@hotmail.com","gender":"","firstname":"Lucius Galeana","city":"Winston Salem","account_type":"Commercial","phone":"7556142383","address":"1505 Barrington Way Ct","state":"NC","zip":"27106-4798","dob":"20-11-1949","primary":"","ApplicantID":"","agency_id":"","hasActive":"","ClientPolicy":""},{"agent":"Alex Watson","userType":"Active Client","policy_mode":"12","producer":"Emiko Lobo","policy_number":"52W3TI0WSRYZ","premium_amount_written":"","premium_amount":"1495","policy_type":"Single","company_name":"Nationwide Mut Fire Ins Co","category_name":"Homeowners","policy_start_date":"05-07-2018","policy_end_date":"05-07-2019","csr":"Harley Kerr","account_name":"Humberto Boykins & Angelo Pugh","email":"jimxugle@me.com","gender":"","firstname":"Humberto Boykins","city":"Winston Salem","account_type":"Commercial","phone":"5813432048","address":"2970 Kedron Ct","state":"NC","zip":"27106-5009","dob":"15-11-1951","primary":"","ApplicantID":"","agency_id":"","hasActive":"","ClientPolicy":""},{"agent":"Alex Watson","userType":"Active Client","policy_mode":"6","producer":"Xavier Hughes","policy_number":"1L4U1S4WVUS0","premium_amount_written":"","premium_amount":"644.01","policy_type":"Single","company_name":"Nationwide Mut Ins Co_Copy","category_name":"Personal Auto","policy_start_date":"01-02-2019","policy_end_date":"01-08-2019","csr":"Todd Mckee","account_name":"Chia Duque & Moses Wilcox","email":"dwendlan@gmail.com","gender":"","firstname":"Chia Duque","city":"Winston Salem","account_type":"Commercial","phone":"7045490404","address":"2970 Kedron Ct","state":"NC","zip":"27106-5009","dob":"24-09-1952","primary":"","ApplicantID":"","agency_id":"","hasActive":"","ClientPolicy":""},{"agent":"Alex Watson","userType":"Active Client","policy_mode":"6","producer":"Aubrey Loder","policy_number":"CNJHKXQCQVBM","premium_amount_written":"","premium_amount":"548.38","policy_type":"Single","company_name":"Nationwide Mut Ins Co_Copy","category_name":"Personal Auto","policy_start_date":"14-11-2018","policy_end_date":"14-05-2019","csr":"Sherri Austin","account_name":"Shawnda Armond & Long Miranda","email":"vertigo@msn.com","gender":"","firstname":"Shawnda Armond","city":"Winston Salem","account_type":"Commercial","phone":"9103623679","address":"2460 Lake Forest Dr","state":"NC","zip":"27106-9734","dob":"09-08-1960","primary":"","ApplicantID":"","agency_id":"","hasActive":"","ClientPolicy":""},{"agent":"Rita Ora","userType":"Active Client","policy_mode":"6","producer":"Jared Roan","policy_number":"F52TX9SNXJCD","premium_amount_written":"","premium_amount":"1030.14","policy_type":"Single","company_name":"Nationwide Mut Ins Co_Copy","category_name":"Personal Auto","policy_start_date":"2019-02-01","policy_end_date":"2019-08-01","csr":"Adrian Roy","account_name":"Forrest Yousef & Hobert Torres","email":"grady@live.com","gender":"Female","firstname":"Forrest Yousef","city":"Winston Salem","account_type":"Personal","phone":"6010904157","address":"1219 Wedgewood Dr","state":"NC","zip":"27103-4211","dob":"1961-06-17","primary":"","ApplicantID":"","agency_id":"","hasActive":"","ClientPolicy":""},{"agent":"Rita Ora","userType":"Active Client","policy_mode":"12","producer":"Alayna Meekins","policy_number":"3GEV9AWROSQC","premium_amount_written":"","premium_amount":"682","policy_type":"Single","company_name":"Nationwide Mut Fire Ins Co_Copy","category_name":"Homeowners","policy_start_date":"2018-11-01","policy_end_date":"2019-11-01","csr":"Darwin Miranda","account_name":"Jasmin Kimberlin & Peggy Hoffman","email":"tfinniga@yahoo.com","gender":"Female","firstname":"Jasmin Kimberlin","city":"Lewisville","account_type":"Personal","phone":"7824606826","address":"7915 Curtina Ln","state":"NC","zip":"27023-9783","dob":"1944-08-12","primary":"","ApplicantID":"","agency_id":"","hasActive":"","ClientPolicy":""}]